[{"name":"sql.active_record","payload":{"sql":"SELECT  \"admin_users\".* FROM \"admin_users\" WHERE \"admin_users\".\"id\" = ?  ORDER BY \"admin_users\".\"id\" ASC LIMIT 1","name":"AdminUser Load","connection_id":70365587411300,"statement_name":null,"binds":[[{"name":"id","cast_type":{"precision":null,"scale":null,"limit":null,"range":"-2147483648...2147483648"},"sql_type":"INTEGER","null":false,"default":null,"default_function":null},1]]},"time":"2016-02-13T21:32:22.892-05:00","transaction_id":"404262944964c0352f21","end":"2016-02-13T21:32:22.893-05:00","children":[],"duration":0.262},{"name":"sql.active_record","payload":{"sql":"SELECT  \"events\".* FROM \"events\" WHERE \"events\".\"slug\" = ?  ORDER BY \"events\".\"id\" ASC LIMIT 1","name":"Event Load","connection_id":70365587411300,"statement_name":null,"binds":[[{"name":"slug","cast_type":{"precision":null,"scale":null,"limit":null},"sql_type":"varchar","null":true,"default":null,"default_function":null},"special-gose-release"]],"line":4,"filename":"/Users/blakeyoder/WebDev/Projects/bfs/app/admin/event.rb","method":"find_resource"},"time":"2016-02-13T21:32:22.895-05:00","transaction_id":"404262944964c0352f21","end":"2016-02-13T21:32:22.895-05:00","children":[],"duration":0.244},{"name":"render_template.action_view","payload":{"identifier":"/Users/blakeyoder/.rvm/gems/ruby-2.3.0/bundler/gems/activeadmin-ab1d8d1a4a1a/app/views/active_admin/resource/edit.html.arb","layout":null},"time":"2016-02-13T21:32:22.904-05:00","transaction_id":"ca7cb44bf35b0b6d4d33","end":"2016-02-13T21:32:23.026-05:00","children":[],"duration":122.183},{"name":"process_action.action_controller","payload":{"controller":"Admin::EventsController","action":"edit","params":{"controller":"admin/events","action":"edit","id":"special-gose-release"},"format":"html","method":"GET","path":"/admin/events/special-gose-release/edit","status":200,"view_runtime":130.19670199719258,"db_runtime":0.15600000000000003},"time":"2016-02-13T21:32:22.891-05:00","transaction_id":"ca7cb44bf35b0b6d4d33","end":"2016-02-13T21:32:23.027-05:00","children":[],"duration":135.336}]